{"source": "ССЦ РК 8.04-08-2025", "file": "ССЦ РК 8.04-08-2025 Сметные цены на строительные материалы, изделия и конструкции. Книги 2, 3, 6. Выпуск 3.docx", "region": null, "region_slug": "common", "book": "combo-2,3,6", "issue": 3, "kind": "rates", "rows": [{"code": "217-103-2300", "name": "Анкер рамный металлический", "unit": "шт.", "isGroup": true}, {"code": "217-103-2303", "name": "10x112 мм", "unit": "шт.", "cargoClass": "1", "grossKg": 0, "otpusknaya": 33, "smetnaya": 33}, {"code": "232-103-0100", "name": "Гипсостружечная плита обычная ГСП", "unit": "м2", "isGroup": true}, {"code": "232-103-0101", "name": "толщиной 10 мм", "unit": "м2", "cargoClass": "2", "grossKg": 12, "otpusknaya": 3626, "smetnaya": 3704}, {"code": "232-103-0200", "name": "Гипсостружечная плита влагостойкая ГСПВ", "unit": "м2", "isGroup": true}, {"code": "232-103-0201", "name": "толщиной 10 мм", "unit": "м2", "cargoClass": "2", "grossKg": 12, "otpusknaya": 3899, "smetnaya": 3980}, {"code": "232-104-0100", "name": "Цементно-стружечная плита ЦСП", "unit": "м2", "isGroup": true}, {"code": "232-104-0101", "name": "толщиной 8 мм", "unit": "м2", "cargoClass": "2", "grossKg": 11, "otpusknaya": 2940, "smetnaya": 3005}, {"code": "232-104-0102", "name": "толщиной 10 мм", "unit": "м2", "cargoClass": "2", "grossKg": 14, "otpusknaya": 3418, "smetnaya": 3497}, {"code": "232-104-0103", "name": "толщиной 12 мм", "unit": "м2", "cargoClass": "2", "grossKg": 16, "otpusknaya": 3848, "smetnaya": 3938}, {"code": "232-104-0104", "name": "толщиной 16 мм", "unit": "м2", "cargoClass": "2", "grossKg": 22, "otpusknaya": 4706, "smetnaya": 4822}, {"code": "232-104-0105", "name": "толщиной 20 мм", "unit": "м2", "cargoClass": "2", "grossKg": 27, "otpusknaya": 5827, "smetnaya": 5971}, {"code": "233-101-0100", "name": "Линолеум поливинилхлоридный ГОСТ 7251-2016", "unit": "м2", "isGroup": true}, {"code": "233-101-0105", "name": "коммерческий гетерогенный, класс 33, 34", "unit": "м2", "cargoClass": "1", "grossKg": 3, "otpusknaya": 5037, "smetnaya": 5105}, {"code": "233-101-0106", "name": "коммерческий гомогенный, класс 33, 34", "unit": "м2", "cargoClass": "1", "grossKg": 3, "otpusknaya": 4156, "smetnaya": 4213}, {"code": "233-101-0107", "name": "коммерческий гетерогенный, класс 41, 42, 43", "unit": "м2", "cargoClass": "1", "grossKg": 3, "otpusknaya": 5247, "smetnaya": 5318}, {"code": "233-101-0109", "name": "коммерческий гетерогенный с защитным лаком, с антибактериальными свойствами, класс 34-43, поверхность полиуретановая, толщина защитного слоя 1 мм", "unit": "м2", "cargoClass": "1", "grossKg": 3, "otpusknaya": 5462, "smetnaya": 5534}, {"code": "241-113-0200", "name": "Тройник приварной бесшовный переходной ГОСТ 17380-2001 (ГОСТ 17376-2001)", "unit": "шт.", "isGroup": true}, {"code": "241-113-0228", "name": "размерами 273х7,0-159х7,0 мм", "unit": "шт.", "cargoClass": "1", "grossKg": 20, "otpusknaya": 39282, "smetnaya": 39505}, {"code": "241-113-0229", "name": "размерами 273х8,0-159х4,5 мм", "unit": "шт.", "cargoClass": "1", "grossKg": 20, "otpusknaya": 39282, "smetnaya": 39507}, {"code": "241-113-0230", "name": "размерами 273x8,0-159x8,0 мм", "unit": "шт.", "cargoClass": "1", "grossKg": 28, "otpusknaya": 39282, "smetnaya": 39524}, {"code": "241-113-0231", "name": "размерами 273х8,0-219х6,0 мм", "unit": "шт.", "cargoClass": "1", "grossKg": 29, "otpusknaya": 39282, "smetnaya": 39526}, {"code": "241-113-0232", "name": "размерами 273х8,0-219х8,0 мм", "unit": "шт.", "cargoClass": "1", "grossKg": 30, "otpusknaya": 39282, "smetnaya": 39529}, {"code": "241-301-0800", "name": "Труба пластиковая, армированная стекловолокном GRP с усиленным внутренним слоем Grey для водоснабжения, PN 1, SN 5000 СТ РК EN 1796-2018", "unit": "м", "isGroup": true}, {"code": "241-301-0801", "name": "DN 300", "unit": "м", "cargoClass": "3", "grossKg": 10, "otpusknaya": 55016, "smetnaya": 55716}, {"code": "241-301-0802", "name": "DN 350", "unit": "м", "cargoClass": "3", "grossKg": 14, "otpusknaya": 63134, "smetnaya": 63947}, {"code": "241-301-0803", "name": "DN 400", "unit": "м", "cargoClass": "3", "grossKg": 18, "otpusknaya": 71933, "smetnaya": 72867}, {"code": "241-301-0804", "name": "DN 500", "unit": "м", "cargoClass": "3", "grossKg": 29, "otpusknaya": 91414, "smetnaya": 92623}, {"code": "241-301-0805", "name": "DN 600", "unit": "м", "cargoClass": "3", "grossKg": 40, "otpusknaya": 113855, "smetnaya": 115373}, {"code": "241-301-0806", "name": "DN 700", "unit": "м", "cargoClass": "3", "grossKg": 53, "otpusknaya": 141157, "smetnaya": 143054}, {"code": "241-301-0807", "name": "DN 800", "unit": "м", "cargoClass": "3", "grossKg": 69, "otpusknaya": 172742, "smetnaya": 175079}, {"code": "241-301-0808", "name": "DN 900", "unit": "м", "cargoClass": "3", "grossKg": 87, "otpusknaya": 208234, "smetnaya": 211066}, {"code": "241-301-0809", "name": "DN 1000", "unit": "м", "cargoClass": "3", "grossKg": 106, "otpusknaya": 219639, "smetnaya": 222681}, {"code": "241-301-0810", "name": "DN 1200", "unit": "м", "cargoClass": "3", "grossKg": 152, "otpusknaya": 298211, "smetnaya": 302372}, {"code": "241-301-0811", "name": "DN 1400", "unit": "м", "cargoClass": "3", "grossKg": 207, "otpusknaya": 390973, "smetnaya": 396458}, {"code": "241-301-0812", "name": "DN 1600", "unit": "м", "cargoClass": "3", "grossKg": 270, "otpusknaya": 495535, "smetnaya": 502516}, {"code": "241-301-0813", "name": "DN 1800", "unit": "м", "cargoClass": "3", "grossKg": 341, "otpusknaya": 553616, "smetnaya": 561567}, {"code": "241-301-0814", "name": "DN 2000", "unit": "м", "cargoClass": "3", "grossKg": 420, "otpusknaya": 674200, "smetnaya": 683900}, {"code": "241-301-0815", "name": "DN 2200", "unit": "м", "cargoClass": "3", "grossKg": 507, "otpusknaya": 811086, "smetnaya": 822762}, {"code": "241-301-0816", "name": "DN 2400", "unit": "м", "cargoClass": "3", "grossKg": 602, "otpusknaya": 965521, "smetnaya": 979415}, {"code": "241-301-0817", "name": "DN 3000", "unit": "м", "cargoClass": "3", "grossKg": 938, "otpusknaya": 1496541, "smetnaya": 1518096}, {"code": "241-301-0900", "name": "Труба пластиковая, армированная стекловолокном GRP с усиленным внутренним слоем Grey для водоснабжения, PN 6, SN 5000 СТ РК EN 1796-2018", "unit": "м", "isGroup": true}, {"code": "241-301-0901", "name": "DN 300", "unit": "м", "cargoClass": "3", "grossKg": 10, "otpusknaya": 55135, "smetnaya": 55837}, {"code": "241-301-0902", "name": "DN 350", "unit": "м", "cargoClass": "3", "grossKg": 14, "otpusknaya": 63379, "smetnaya": 64195}, {"code": "241-301-0903", "name": "DN 400", "unit": "м", "cargoClass": "3", "grossKg": 18, "otpusknaya": 72255, "smetnaya": 73193}, {"code": "241-301-0904", "name": "DN 500", "unit": "м", "cargoClass": "3", "grossKg": 29, "otpusknaya": 92005, "smetnaya": 93220}, {"code": "241-301-0905", "name": "DN 600", "unit": "м", "cargoClass": "3", "grossKg": 40, "otpusknaya": 114445, "smetnaya": 115970}, {"code": "241-301-0906", "name": "DN 700", "unit": "м", "cargoClass": "3", "grossKg": 53, "otpusknaya": 141998, "smetnaya": 143905}, {"code": "241-301-0907", "name": "DN 800", "unit": "м", "cargoClass": "3", "grossKg": 69, "otpusknaya": 174126, "smetnaya": 176480}, {"code": "241-301-0908", "name": "DN 900", "unit": "м", "cargoClass": "3", "grossKg": 87, "otpusknaya": 210298, "smetnaya": 213155}, {"code": "241-301-0909", "name": "DN 1000", "unit": "м", "cargoClass": "3", "grossKg": 106, "otpusknaya": 221942, "smetnaya": 225011}, {"code": "241-301-0910", "name": "DN 1200", "unit": "м", "cargoClass": "3", "grossKg": 152, "otpusknaya": 301313, "smetnaya": 305511}, {"code": "241-301-0911", "name": "DN 1400", "unit": "м", "cargoClass": "3", "grossKg": 207, "otpusknaya": 393956, "smetnaya": 399477}, {"code": "241-301-0912", "name": "DN 1600", "unit": "м", "cargoClass": "3", "grossKg": 270, "otpusknaya": 499185, "smetnaya": 506210}, {"code": "241-301-0913", "name": "DN 1800", "unit": "м", "cargoClass": "3", "grossKg": 341, "otpusknaya": 557374, "smetnaya": 565370}, {"code": "241-301-0914", "name": "DN 2000", "unit": "м", "cargoClass": "3", "grossKg": 420, "otpusknaya": 679228, "smetnaya": 688989}, {"code": "241-301-0915", "name": "DN 2200", "unit": "м", "cargoClass": "3", "grossKg": 507, "otpusknaya": 816937, "smetnaya": 828684}, {"code": "241-301-0916", "name": "DN 2400", "unit": "м", "cargoClass": "3", "grossKg": 602, "otpusknaya": 971826, "smetnaya": 985796}, {"code": "241-301-0917", "name": "DN 3000", "unit": "м", "cargoClass": "3", "grossKg": 938, "otpusknaya": 1502536, "smetnaya": 1524163}, {"code": "241-301-1000", "name": "Труба пластиковая, армированная стекловолокном GRP с усиленным внутренним слоем Grey для водоснабжения, PN 10, SN 5000 СТ РК EN 1796-2018", "unit": "м", "isGroup": true}, {"code": "241-301-1001", "name": "DN 300", "unit": "м", "cargoClass": "3", "grossKg": 10, "otpusknaya": 55248, "smetnaya": 55952}, {"code": "241-301-1002", "name": "DN 350", "unit": "м", "cargoClass": "3", "grossKg": 14, "otpusknaya": 63617, "smetnaya": 64434}, {"code": "241-301-1003", "name": "DN 400", "unit": "м", "cargoClass": "3", "grossKg": 18, "otpusknaya": 72571, "smetnaya": 73509}, {"code": "241-301-1004", "name": "DN 500", "unit": "м", "cargoClass": "3", "grossKg": 27, "otpusknaya": 92589, "smetnaya": 93804}, {"code": "241-301-1005", "name": "DN 600", "unit": "м", "cargoClass": "3", "grossKg": 36, "otpusknaya": 115036, "smetnaya": 116554}, {"code": "241-301-1006", "name": "DN 700", "unit": "м", "cargoClass": "3", "grossKg": 49, "otpusknaya": 142839, "smetnaya": 144741}, {"code": "241-301-1007", "name": "DN 800", "unit": "м", "cargoClass": "3", "grossKg": 63, "otpusknaya": 175504, "smetnaya": 177851}, {"code": "241-301-1008", "name": "DN 900", "unit": "м", "cargoClass": "3", "grossKg": 81, "otpusknaya": 212356, "smetnaya": 215215}, {"code": "241-301-1009", "name": "DN 1000", "unit": "м", "cargoClass": "3", "grossKg": 99, "otpusknaya": 224238, "smetnaya": 227309}, {"code": "241-301-1010", "name": "DN 1200", "unit": "м", "cargoClass": "3", "grossKg": 142, "otpusknaya": 304408, "smetnaya": 308606}, {"code": "241-301-1011", "name": "DN 1400", "unit": "м", "cargoClass": "3", "grossKg": 192, "otpusknaya": 396932, "smetnaya": 402432}, {"code": "241-301-1012", "name": "DN 1600", "unit": "м", "cargoClass": "3", "grossKg": 250, "otpusknaya": 502830, "smetnaya": 509822}, {"code": "241-301-1013", "name": "DN 1800", "unit": "м", "cargoClass": "3", "grossKg": 316, "otpusknaya": 561126, "smetnaya": 569071}, {"code": "241-301-1014", "name": "DN 2000", "unit": "м", "cargoClass": "3", "grossKg": 389, "otpusknaya": 684251, "smetnaya": 693953}, {"code": "241-301-1015", "name": "DN 2200", "unit": "м", "cargoClass": "3", "grossKg": 469, "otpusknaya": 822789, "smetnaya": 834461}, {"code": "241-301-1016", "name": "DN 2400", "unit": "м", "cargoClass": "3", "grossKg": 558, "otpusknaya": 978131, "smetnaya": 992008}, {"code": "241-301-1017", "name": "DN 3000", "unit": "м", "cargoClass": "3", "grossKg": 869, "otpusknaya": 1508531, "smetnaya": 1529965}, {"code": "241-301-1100", "name": "Труба пластиковая, армированная стекловолокном GRP с усиленным внутренним слоем Grey для водоснабжения, PN 16, SN 5000 СТ РК EN 1796-2018", "unit": "м", "isGroup": true}, {"code": "241-301-1101", "name": "DN 300", "unit": "м", "cargoClass": "3", "grossKg": 10, "otpusknaya": 57414, "smetnaya": 58139}, {"code": "241-301-1102", "name": "DN 350", "unit": "м", "cargoClass": "3", "grossKg": 13, "otpusknaya": 66325, "smetnaya": 67171}, {"code": "241-301-1103", "name": "DN 400", "unit": "м", "cargoClass": "3", "grossKg": 16, "otpusknaya": 76013, "smetnaya": 76986}, {"code": "241-301-1104", "name": "DN 500", "unit": "м", "cargoClass": "3", "grossKg": 25, "otpusknaya": 98411, "smetnaya": 99688}, {"code": "241-301-1105", "name": "DN 600", "unit": "м", "cargoClass": "3", "grossKg": 33, "otpusknaya": 122952, "smetnaya": 124554}, {"code": "241-301-1106", "name": "DN 700", "unit": "м", "cargoClass": "3", "grossKg": 44, "otpusknaya": 153773, "smetnaya": 155787}, {"code": "241-301-1107", "name": "DN 800", "unit": "м", "cargoClass": "3", "grossKg": 57, "otpusknaya": 189331, "smetnaya": 191821}, {"code": "241-301-1108", "name": "DN 900", "unit": "м", "cargoClass": "3", "grossKg": 72, "otpusknaya": 228903, "smetnaya": 231926}, {"code": "241-301-1109", "name": "DN 1000", "unit": "м", "cargoClass": "3", "grossKg": 89, "otpusknaya": 242097, "smetnaya": 245344}, {"code": "241-301-1110", "name": "DN 1200", "unit": "м", "cargoClass": "3", "grossKg": 126, "otpusknaya": 330380, "smetnaya": 334828}, {"code": "241-301-1111", "name": "DN 1400", "unit": "м", "cargoClass": "3", "grossKg": 171, "otpusknaya": 432353, "smetnaya": 438197}, {"code": "241-301-1112", "name": "DN 1600", "unit": "м", "cargoClass": "3", "grossKg": 222, "otpusknaya": 551051, "smetnaya": 558515}, {"code": "241-301-1113", "name": "DN 1800", "unit": "м", "cargoClass": "3", "grossKg": 280, "otpusknaya": 615748, "smetnaya": 624211}, {"code": "241-301-1114", "name": "DN 2000", "unit": "м", "cargoClass": "3", "grossKg": 345, "otpusknaya": 750182, "smetnaya": 760507}, {"code": "241-301-1115", "name": "DN 2200", "unit": "м", "cargoClass": "3", "grossKg": 416, "otpusknaya": 901062, "smetnaya": 913470}, {"code": "241-301-1116", "name": "DN 2400", "unit": "м", "cargoClass": "3", "grossKg": 495, "otpusknaya": 1067875, "smetnaya": 1082587}, {"code": "241-301-1117", "name": "DN 3000", "unit": "м", "cargoClass": "3", "grossKg": 770, "otpusknaya": 1643037, "smetnaya": 1665705}, {"code": "241-301-1200", "name": "Труба пластиковая, армированная стекловолокном GRP с усиленным внутренним слоем Grey для водоснабжения, PN 20, SN 5000 СТ РК EN 1796-2018", "unit": "м", "isGroup": true}, {"code": "241-301-1201", "name": "DN 300", "unit": "м", "cargoClass": "3", "grossKg": 9, "otpusknaya": 58756, "smetnaya": 59495}, {"code": "241-301-1202", "name": "DN 350", "unit": "м", "cargoClass": "3", "grossKg": 12, "otpusknaya": 68431, "smetnaya": 69298}, {"code": "241-301-1203", "name": "DN 400", "unit": "м", "cargoClass": "3", "grossKg": 16, "otpusknaya": 78965, "smetnaya": 79974}, {"code": "241-301-1204", "name": "DN 500", "unit": "м", "cargoClass": "3", "grossKg": 24, "otpusknaya": 102611, "smetnaya": 103934}, {"code": "241-301-1205", "name": "DN 600", "unit": "м", "cargoClass": "3", "grossKg": 32, "otpusknaya": 129084, "smetnaya": 130755}, {"code": "241-301-1206", "name": "DN 700", "unit": "м", "cargoClass": "3", "grossKg": 43, "otpusknaya": 162261, "smetnaya": 164373}, {"code": "241-301-1207", "name": "DN 800", "unit": "м", "cargoClass": "3", "grossKg": 55, "otpusknaya": 200121, "smetnaya": 202734}, {"code": "241-301-1208", "name": "DN 900", "unit": "м", "cargoClass": "3", "grossKg": 70, "otpusknaya": 242223, "smetnaya": 245398}, {"code": "241-301-1209", "name": "DN 1000", "unit": "м", "cargoClass": "3", "grossKg": 85, "otpusknaya": 257034, "smetnaya": 260444}, {"code": "241-301-1210", "name": "DN 1200", "unit": "м", "cargoClass": "3", "grossKg": 122, "otpusknaya": 352946, "smetnaya": 357649}, {"code": "241-301-1211", "name": "DN 1400", "unit": "м", "cargoClass": "3", "grossKg": 165, "otpusknaya": 464206, "smetnaya": 470409}, {"code": "241-301-1212", "name": "DN 1600", "unit": "м", "cargoClass": "3", "grossKg": 214, "otpusknaya": 591005, "smetnaya": 598918}, {"code": "241-301-1213", "name": "DN 1800", "unit": "м", "cargoClass": "3", "grossKg": 270, "otpusknaya": 660498, "smetnaya": 669459}, {"code": "241-301-1214", "name": "DN 2000", "unit": "м", "cargoClass": "3", "grossKg": 332, "otpusknaya": 804775, "smetnaya": 815705}, {"code": "241-301-1215", "name": "DN 2200", "unit": "м", "cargoClass": "3", "grossKg": 401, "otpusknaya": 966189, "smetnaya": 979320}, {"code": "241-301-1216", "name": "DN 2400", "unit": "м", "cargoClass": "3", "grossKg": 476, "otpusknaya": 1145433, "smetnaya": 1161003}, {"code": "241-301-1300", "name": "Труба пластиковая, армированная стекловолокном GRP с усиленным внутренним слоем Grey для водоснабжения, PN 25, SN 5000 СТ РК EN 1796-2018", "unit": "м", "isGroup": true}, {"code": "241-301-1301", "name": "DN 300", "unit": "м", "cargoClass": "3", "grossKg": 9, "otpusknaya": 61201, "smetnaya": 61970}, {"code": "241-301-1302", "name": "DN 350", "unit": "м", "cargoClass": "3", "grossKg": 12, "otpusknaya": 71515, "smetnaya": 72419}, {"code": "241-301-1303", "name": "DN 400", "unit": "м", "cargoClass": "3", "grossKg": 15, "otpusknaya": 82616, "smetnaya": 83665}, {"code": "241-301-1304", "name": "DN 500", "unit": "м", "cargoClass": "3", "grossKg": 23, "otpusknaya": 107938, "smetnaya": 109321}, {"code": "241-301-1305", "name": "DN 600", "unit": "м", "cargoClass": "3", "grossKg": 31, "otpusknaya": 136832, "smetnaya": 138593}, {"code": "241-301-1306", "name": "DN 700", "unit": "м", "cargoClass": "3", "grossKg": 42, "otpusknaya": 172062, "smetnaya": 174288}, {"code": "241-301-1307", "name": "DN 800", "unit": "м", "cargoClass": "3", "grossKg": 54, "otpusknaya": 213370, "smetnaya": 216137}, {"code": "241-301-1308", "name": "DN 900", "unit": "м", "cargoClass": "3", "grossKg": 68, "otpusknaya": 260351, "smetnaya": 263735}, {"code": "241-301-1309", "name": "DN 1000", "unit": "м", "cargoClass": "3", "grossKg": 83, "otpusknaya": 277733, "smetnaya": 281384}, {"code": "241-301-1310", "name": "DN 1200", "unit": "м", "cargoClass": "3", "grossKg": 119, "otpusknaya": 383201, "smetnaya": 388255}, {"code": "241-301-1311", "name": "DN 1400", "unit": "м", "cargoClass": "3", "grossKg": 160, "otpusknaya": 504142, "smetnaya": 510805}, {"code": "241-301-1312", "name": "DN 1600", "unit": "м", "cargoClass": "3", "grossKg": 208, "otpusknaya": 641201, "smetnaya": 649693}, {"code": "241-301-1313", "name": "DN 1800", "unit": "м", "cargoClass": "3", "grossKg": 262, "otpusknaya": 717762, "smetnaya": 727380}, {"code": "241-301-1314", "name": "DN 2000", "unit": "м", "cargoClass": "3", "grossKg": 323, "otpusknaya": 873802, "smetnaya": 885526}, {"code": "241-301-1315", "name": "DN 2200", "unit": "м", "cargoClass": "3", "grossKg": 377, "otpusknaya": 1022034, "smetnaya": 1035743}, {"code": "241-301-1316", "name": "DN 2400", "unit": "м", "cargoClass": "3", "grossKg": 434, "otpusknaya": 1180268, "smetnaya": 1196096}, {"code": "241-301-1400", "name": "Труба пластиковая, армированная стекловолокном GRP с усиленным внутренним слоем Grey для водоснабжения, PN 1, SN 10000 СТ РК EN 1796-2018", "unit": "м", "isGroup": true}, {"code": "241-301-1401", "name": "DN 300", "unit": "м", "cargoClass": "3", "grossKg": 13, "otpusknaya": 60903, "smetnaya": 61684}, {"code": "241-301-1402", "name": "DN 350", "unit": "м", "cargoClass": "3", "grossKg": 18, "otpusknaya": 70507, "smetnaya": 71420}, {"code": "241-301-1403", "name": "DN 400", "unit": "м", "cargoClass": "3", "grossKg": 22, "otpusknaya": 80785, "smetnaya": 81840}, {"code": "241-301-1404", "name": "DN 500", "unit": "м", "cargoClass": "3", "grossKg": 35, "otpusknaya": 104227, "smetnaya": 105612}, {"code": "241-301-1405", "name": "DN 600", "unit": "м", "cargoClass": "3", "grossKg": 48, "otpusknaya": 130873, "smetnaya": 132628}, {"code": "241-301-1406", "name": "DN 700", "unit": "м", "cargoClass": "3", "grossKg": 66, "otpusknaya": 164122, "smetnaya": 166345}, {"code": "241-301-1407", "name": "DN 800", "unit": "м", "cargoClass": "3", "grossKg": 85, "otpusknaya": 202191, "smetnaya": 204943}, {"code": "241-301-1408", "name": "DN 900", "unit": "м", "cargoClass": "3", "grossKg": 107, "otpusknaya": 244973, "smetnaya": 248323}, {"code": "241-301-1409", "name": "DN 1000", "unit": "м", "cargoClass": "3", "grossKg": 133, "otpusknaya": 260929, "smetnaya": 264570}, {"code": "241-301-1410", "name": "DN 1200", "unit": "м", "cargoClass": "3", "grossKg": 191, "otpusknaya": 356984, "smetnaya": 362000}, {"code": "241-301-1411", "name": "DN 1400", "unit": "м", "cargoClass": "3", "grossKg": 259, "otpusknaya": 468656, "smetnaya": 475273}, {"code": "241-301-1412", "name": "DN 1600", "unit": "м", "cargoClass": "3", "grossKg": 337, "otpusknaya": 597054, "smetnaya": 605510}, {"code": "241-301-1413", "name": "DN 1800", "unit": "м", "cargoClass": "3", "grossKg": 425, "otpusknaya": 669028, "smetnaya": 678686}, {"code": "241-301-1414", "name": "DN 2000", "unit": "м", "cargoClass": "3", "grossKg": 523, "otpusknaya": 818476, "smetnaya": 830303}, {"code": "241-301-1415", "name": "DN 2200", "unit": "м", "cargoClass": "3", "grossKg": 632, "otpusknaya": 989399, "smetnaya": 1003695}, {"code": "241-301-1416", "name": "DN 2400", "unit": "м", "cargoClass": "3", "grossKg": 750, "otpusknaya": 1185816, "smetnaya": 1202921}, {"code": "241-301-1500", "name": "Труба пластиковая, армированная стекловолокном GRP с усиленным внутренним слоем Grey для водоснабжения, PN 6, SN 10000 СТ РК EN 1796-2018", "unit": "м", "isGroup": true}, {"code": "241-301-1501", "name": "DN 300", "unit": "м", "cargoClass": "3", "grossKg": 13, "otpusknaya": 60951, "smetnaya": 61732}, {"code": "241-301-1502", "name": "DN 350", "unit": "м", "cargoClass": "3", "grossKg": 18, "otpusknaya": 70578, "smetnaya": 71492}, {"code": "241-301-1503", "name": "DN 400", "unit": "м", "cargoClass": "3", "grossKg": 22, "otpusknaya": 80868, "smetnaya": 81925}, {"code": "241-301-1504", "name": "DN 500", "unit": "м", "cargoClass": "3", "grossKg": 35, "otpusknaya": 104353, "smetnaya": 105739}, {"code": "241-301-1505", "name": "DN 600", "unit": "м", "cargoClass": "3", "grossKg": 48, "otpusknaya": 131046, "smetnaya": 132803}, {"code": "241-301-1506", "name": "DN 700", "unit": "м", "cargoClass": "3", "grossKg": 66, "otpusknaya": 164415, "smetnaya": 166641}, {"code": "241-301-1507", "name": "DN 800", "unit": "м", "cargoClass": "3", "grossKg": 85, "otpusknaya": 202752, "smetnaya": 205511}, {"code": "241-301-1508", "name": "DN 900", "unit": "м", "cargoClass": "3", "grossKg": 107, "otpusknaya": 245659, "smetnaya": 249017}, {"code": "241-301-1509", "name": "DN 1000", "unit": "м", "cargoClass": "3", "grossKg": 133, "otpusknaya": 261621, "smetnaya": 265270}, {"code": "241-301-1510", "name": "DN 1200", "unit": "м", "cargoClass": "3", "grossKg": 191, "otpusknaya": 357969, "smetnaya": 362996}, {"code": "241-301-1511", "name": "DN 1400", "unit": "м", "cargoClass": "3", "grossKg": 259, "otpusknaya": 469903, "smetnaya": 476535}, {"code": "241-301-1512", "name": "DN 1600", "unit": "м", "cargoClass": "3", "grossKg": 337, "otpusknaya": 598605, "smetnaya": 607080}, {"code": "241-301-1513", "name": "DN 1800", "unit": "м", "cargoClass": "3", "grossKg": 425, "otpusknaya": 670680, "smetnaya": 680358}, {"code": "241-301-1514", "name": "DN 2000", "unit": "м", "cargoClass": "3", "grossKg": 523, "otpusknaya": 820928, "smetnaya": 832784}, {"code": "241-301-1515", "name": "DN 2200", "unit": "м", "cargoClass": "3", "grossKg": 632, "otpusknaya": 992650, "smetnaya": 1006985}, {"code": "241-301-1516", "name": "DN 2400", "unit": "м", "cargoClass": "3", "grossKg": 750, "otpusknaya": 1189866, "smetnaya": 1207020}, {"code": "241-301-1600", "name": "Труба пластиковая, армированная стекловолокном GRP с усиленным внутренним слоем Grey для водоснабжения, PN 10, SN 10000 СТ РК EN 1796-2018", "unit": "м", "isGroup": true}, {"code": "241-301-1601", "name": "DN 300", "unit": "м", "cargoClass": "3", "grossKg": 13, "otpusknaya": 60993, "smetnaya": 61774}, {"code": "241-301-1602", "name": "DN 350", "unit": "м", "cargoClass": "3", "grossKg": 18, "otpusknaya": 70644, "smetnaya": 71559}, {"code": "241-301-1603", "name": "DN 400", "unit": "м", "cargoClass": "3", "grossKg": 22, "otpusknaya": 80952, "smetnaya": 82009}, {"code": "241-301-1604", "name": "DN 500", "unit": "м", "cargoClass": "3", "grossKg": 35, "otpusknaya": 104478, "smetnaya": 105866}, {"code": "241-301-1605", "name": "DN 600", "unit": "м", "cargoClass": "3", "grossKg": 48, "otpusknaya": 131213, "smetnaya": 132972}, {"code": "241-301-1606", "name": "DN 700", "unit": "м", "cargoClass": "3", "grossKg": 66, "otpusknaya": 164701, "smetnaya": 166930}, {"code": "241-301-1607", "name": "DN 800", "unit": "м", "cargoClass": "3", "grossKg": 85, "otpusknaya": 203313, "smetnaya": 206078}, {"code": "241-301-1608", "name": "DN 900", "unit": "м", "cargoClass": "3", "grossKg": 107, "otpusknaya": 246339, "smetnaya": 249705}, {"code": "241-301-1609", "name": "DN 1000", "unit": "м", "cargoClass": "3", "grossKg": 133, "otpusknaya": 262313, "smetnaya": 265971}, {"code": "241-301-1610", "name": "DN 1200", "unit": "м", "cargoClass": "3", "grossKg": 191, "otpusknaya": 358953, "smetnaya": 363992}, {"code": "241-301-1611", "name": "DN 1400", "unit": "м", "cargoClass": "3", "grossKg": 259, "otpusknaya": 471143, "smetnaya": 477790}, {"code": "241-301-1612", "name": "DN 1600", "unit": "м", "cargoClass": "3", "grossKg": 337, "otpusknaya": 600156, "smetnaya": 608649}, {"code": "241-301-1613", "name": "DN 1800", "unit": "м", "cargoClass": "3", "grossKg": 425, "otpusknaya": 672327, "smetnaya": 682024}, {"code": "241-301-1614", "name": "DN 2000", "unit": "м", "cargoClass": "3", "grossKg": 523, "otpusknaya": 823380, "smetnaya": 835265}, {"code": "241-301-1615", "name": "DN 2200", "unit": "м", "cargoClass": "3", "grossKg": 632, "otpusknaya": 995901, "smetnaya": 1010275}, {"code": "241-301-1616", "name": "DN 2400", "unit": "м", "cargoClass": "3", "grossKg": 750, "otpusknaya": 1193916, "smetnaya": 1211119}, {"code": "241-301-1700", "name": "Труба пластиковая, армированная стекловолокном GRP с усиленным внутренним слоем Grey для водоснабжения, PN 16, SN 10000 СТ РК EN 1796-2018", "unit": "м", "isGroup": true}, {"code": "241-301-1701", "name": "DN 300", "unit": "м", "cargoClass": "3", "grossKg": 12, "otpusknaya": 61893, "smetnaya": 62682}, {"code": "241-301-1702", "name": "DN 350", "unit": "м", "cargoClass": "3", "grossKg": 16, "otpusknaya": 71825, "smetnaya": 72748}, {"code": "241-301-1703", "name": "DN 400", "unit": "м", "cargoClass": "3", "grossKg": 21, "otpusknaya": 82640, "smetnaya": 83712}, {"code": "241-301-1704", "name": "DN 500", "unit": "м", "cargoClass": "3", "grossKg": 32, "otpusknaya": 107514, "smetnaya": 108927}, {"code": "241-301-1705", "name": "DN 600", "unit": "м", "cargoClass": "3", "grossKg": 43, "otpusknaya": 135884, "smetnaya": 137679}, {"code": "241-301-1706", "name": "DN 700", "unit": "м", "cargoClass": "3", "grossKg": 58, "otpusknaya": 170958, "smetnaya": 173232}, {"code": "241-301-1707", "name": "DN 800", "unit": "м", "cargoClass": "3", "grossKg": 75, "otpusknaya": 211706, "smetnaya": 214534}, {"code": "241-301-1708", "name": "DN 900", "unit": "м", "cargoClass": "3", "grossKg": 95, "otpusknaya": 256485, "smetnaya": 259927}, {"code": "241-301-1709", "name": "DN 1000", "unit": "м", "cargoClass": "3", "grossKg": 117, "otpusknaya": 272364, "smetnaya": 276081}, {"code": "241-301-1710", "name": "DN 1200", "unit": "м", "cargoClass": "3", "grossKg": 167, "otpusknaya": 372845, "smetnaya": 377960}, {"code": "241-301-1711", "name": "DN 1400", "unit": "м", "cargoClass": "3", "grossKg": 226, "otpusknaya": 490691, "smetnaya": 497446}, {"code": "241-301-1712", "name": "DN 1600", "unit": "м", "cargoClass": "3", "grossKg": 294, "otpusknaya": 626718, "smetnaya": 635366}, {"code": "241-301-1713", "name": "DN 1800", "unit": "м", "cargoClass": "3", "grossKg": 372, "otpusknaya": 702552, "smetnaya": 712408}, {"code": "241-301-1714", "name": "DN 2000", "unit": "м", "cargoClass": "3", "grossKg": 457, "otpusknaya": 859098, "smetnaya": 871160}, {"code": "241-301-1715", "name": "DN 2200", "unit": "м", "cargoClass": "3", "grossKg": 552, "otpusknaya": 1035407, "smetnaya": 1049948}, {"code": "241-301-1716", "name": "DN 2400", "unit": "м", "cargoClass": "3", "grossKg": 657, "otpusknaya": 1234031, "smetnaya": 1251359}, {"code": "241-301-1800", "name": "Труба пластиковая, армированная стекловолокном GRP с усиленным внутренним слоем Grey для водоснабжения, PN 20, SN 10000 СТ РК EN 1796-2018", "unit": "м", "isGroup": true}, {"code": "241-301-1801", "name": "DN 300", "unit": "м", "cargoClass": "3", "grossKg": 12, "otpusknaya": 63015, "smetnaya": 63817}, {"code": "241-301-1802", "name": "DN 350", "unit": "м", "cargoClass": "3", "grossKg": 16, "otpusknaya": 73454, "smetnaya": 74396}, {"code": "241-301-1803", "name": "DN 400", "unit": "м", "cargoClass": "3", "grossKg": 20, "otpusknaya": 85443, "smetnaya": 86545}, {"code": "241-301-1804", "name": "DN 500", "unit": "м", "cargoClass": "3", "grossKg": 31, "otpusknaya": 111439, "smetnaya": 112895}, {"code": "241-301-1805", "name": "DN 600", "unit": "м", "cargoClass": "3", "grossKg": 41, "otpusknaya": 140847, "smetnaya": 142694}, {"code": "241-301-1806", "name": "DN 700", "unit": "м", "cargoClass": "3", "grossKg": 56, "otpusknaya": 177651, "smetnaya": 179998}, {"code": "241-301-1807", "name": "DN 800", "unit": "м", "cargoClass": "3", "grossKg": 72, "otpusknaya": 220450, "smetnaya": 223372}, {"code": "241-301-1808", "name": "DN 900", "unit": "м", "cargoClass": "3", "grossKg": 90, "otpusknaya": 267079, "smetnaya": 270629}, {"code": "241-301-1809", "name": "DN 1000", "unit": "м", "cargoClass": "3", "grossKg": 111, "otpusknaya": 284318, "smetnaya": 288155}, {"code": "241-301-1810", "name": "DN 1200", "unit": "м", "cargoClass": "3", "grossKg": 159, "otpusknaya": 392101, "smetnaya": 397415}, {"code": "241-301-1811", "name": "DN 1400", "unit": "м", "cargoClass": "3", "grossKg": 215, "otpusknaya": 516675, "smetnaya": 523699}, {"code": "241-301-1812", "name": "DN 1600", "unit": "м", "cargoClass": "3", "grossKg": 280, "otpusknaya": 659359, "smetnaya": 668344}, {"code": "241-301-1813", "name": "DN 1800", "unit": "м", "cargoClass": "3", "grossKg": 353, "otpusknaya": 738652, "smetnaya": 748869}, {"code": "241-301-1814", "name": "DN 2000", "unit": "м", "cargoClass": "3", "grossKg": 435, "otpusknaya": 902625, "smetnaya": 915124}, {"code": "241-301-1815", "name": "DN 2200", "unit": "м", "cargoClass": "3", "grossKg": 525, "otpusknaya": 1086844, "smetnaya": 1101899}, {"code": "241-301-1816", "name": "DN 2400", "unit": "м", "cargoClass": "3", "grossKg": 624, "otpusknaya": 1293807, "smetnaya": 1311725}, {"code": "241-301-1900", "name": "Труба пластиковая, армированная стекловолокном GRP с усиленным внутренним слоем Grey для водоснабжения, PN 25, SN 10000 СТ РК EN 1796-2018", "unit": "м", "isGroup": true}, {"code": "241-301-1901", "name": "DN 300", "unit": "м", "cargoClass": "3", "grossKg": 12, "otpusknaya": 64757, "smetnaya": 65578}, {"code": "241-301-1902", "name": "DN 350", "unit": "м", "cargoClass": "3", "grossKg": 15, "otpusknaya": 76108, "smetnaya": 77079}, {"code": "241-301-1903", "name": "DN 400", "unit": "м", "cargoClass": "3", "grossKg": 20, "otpusknaya": 88098, "smetnaya": 89232}, {"code": "241-301-1904", "name": "DN 500", "unit": "м", "cargoClass": "3", "grossKg": 30, "otpusknaya": 115895, "smetnaya": 117401}, {"code": "241-301-1905", "name": "DN 600", "unit": "м", "cargoClass": "3", "grossKg": 40, "otpusknaya": 147402, "smetnaya": 149325}, {"code": "241-301-1906", "name": "DN 700", "unit": "м", "cargoClass": "3", "grossKg": 54, "otpusknaya": 186444, "smetnaya": 188888}, {"code": "241-301-1907", "name": "DN 800", "unit": "м", "cargoClass": "3", "grossKg": 69, "otpusknaya": 231933, "smetnaya": 234981}, {"code": "241-301-1908", "name": "DN 900", "unit": "м", "cargoClass": "3", "grossKg": 87, "otpusknaya": 282350, "smetnaya": 286071}, {"code": "241-301-1909", "name": "DN 1000", "unit": "м", "cargoClass": "3", "grossKg": 107, "otpusknaya": 302774, "smetnaya": 306817}, {"code": "241-301-1910", "name": "DN 1200", "unit": "м", "cargoClass": "3", "grossKg": 153, "otpusknaya": 418263, "smetnaya": 423869}, {"code": "241-301-1911", "name": "DN 1400", "unit": "м", "cargoClass": "3", "grossKg": 207, "otpusknaya": 551821, "smetnaya": 559236}, {"code": "241-301-1912", "name": "DN 1600", "unit": "м", "cargoClass": "3", "grossKg": 269, "otpusknaya": 704562, "smetnaya": 714048}, {"code": "241-301-1913", "name": "DN 1800", "unit": "м", "cargoClass": "3", "grossKg": 340, "otpusknaya": 788782, "smetnaya": 799551}, {"code": "241-301-1914", "name": "DN 2000", "unit": "м", "cargoClass": "3", "grossKg": 419, "otpusknaya": 963600, "smetnaya": 976770}, {"code": "241-301-1915", "name": "DN 2200", "unit": "м", "cargoClass": "3", "grossKg": 500, "otpusknaya": 1147962, "smetnaya": 1163654}, {"code": "241-301-1916", "name": "DN 2400", "unit": "м", "cargoClass": "3", "grossKg": 580, "otpusknaya": 1334650, "smetnaya": 1352889}, {"code": "241-302-0100", "name": "Труба пластиковая армированная стекловолокном с муфтой для водоснабжения, SN 5000, PN 1 СТ РК 1128-2002", "unit": "м", "isGroup": true}, {"code": "241-302-0101", "name": "DN 300", "unit": "м", "cargoClass": "3", "grossKg": 10, "otpusknaya": 49990, "smetnaya": 50628}, {"code": "241-302-0102", "name": "DN 350", "unit": "м", "cargoClass": "3", "grossKg": 13, "otpusknaya": 57367, "smetnaya": 58105}, {"code": "241-302-0103", "name": "DN 400", "unit": "м", "cargoClass": "3", "grossKg": 17, "otpusknaya": 65362, "smetnaya": 66211}, {"code": "241-302-0105", "name": "DN 500", "unit": "м", "cargoClass": "3", "grossKg": 26, "otpusknaya": 83064, "smetnaya": 84160}, {"code": "241-302-0106", "name": "DN 600", "unit": "м", "cargoClass": "3", "grossKg": 38, "otpusknaya": 103455, "smetnaya": 104842}, {"code": "241-302-0107", "name": "DN 700", "unit": "м", "cargoClass": "3", "grossKg": 51, "otpusknaya": 128263, "smetnaya": 129997}, {"code": "241-302-0108", "name": "DN 800", "unit": "м", "cargoClass": "3", "grossKg": 67, "otpusknaya": 156962, "smetnaya": 159103}, {"code": "241-302-0109", "name": "DN 900", "unit": "м", "cargoClass": "3", "grossKg": 84, "otpusknaya": 189212, "smetnaya": 191805}, {"code": "241-302-0110", "name": "DN 1000", "unit": "м", "cargoClass": "3", "grossKg": 104, "otpusknaya": 199576, "smetnaya": 202369}, {"code": "241-302-0111", "name": "DN 1200", "unit": "м", "cargoClass": "3", "grossKg": 149, "otpusknaya": 227144, "smetnaya": 230441}, {"code": "241-302-0112", "name": "DN 1400", "unit": "м", "cargoClass": "3", "grossKg": 201, "otpusknaya": 298874, "smetnaya": 303232}, {"code": "241-302-0113", "name": "DN 1600", "unit": "м", "cargoClass": "3", "grossKg": 271, "otpusknaya": 361638, "smetnaya": 367016}, {"code": "241-302-0114", "name": "DN 1800", "unit": "м", "cargoClass": "3", "grossKg": 333, "otpusknaya": 401418, "smetnaya": 407512}, {"code": "241-302-0115", "name": "DN 2000", "unit": "м", "cargoClass": "3", "grossKg": 411, "otpusknaya": 612613, "smetnaya": 621540}, {"code": "241-302-0116", "name": "DN 2200", "unit": "м", "cargoClass": "3", "grossKg": 507, "otpusknaya": 736995, "smetnaya": 747783}, {"code": "241-302-0117", "name": "DN 2400", "unit": "м", "cargoClass": "3", "grossKg": 576, "otpusknaya": 877323, "smetnaya": 890059}, {"code": "241-302-0120", "name": "DN 3000", "unit": "м", "cargoClass": "3", "grossKg": 645, "otpusknaya": 1359836, "smetnaya": 1378627}, {"code": "241-302-0200", "name": "Труба пластиковая армированная стекловолокном с муфтой для водоснабжения, SN 5000, PN 6 СТ РК 1128-2002", "unit": "м", "isGroup": true}, {"code": "241-302-0201", "name": "DN 300", "unit": "м", "cargoClass": "3", "grossKg": 10, "otpusknaya": 50099, "smetnaya": 50738}, {"code": "241-302-0202", "name": "DN 350", "unit": "м", "cargoClass": "3", "grossKg": 13, "otpusknaya": 57589, "smetnaya": 58330}, {"code": "241-302-0203", "name": "DN 400", "unit": "м", "cargoClass": "3", "grossKg": 17, "otpusknaya": 65654, "smetnaya": 66507}, {"code": "241-302-0205", "name": "DN 500", "unit": "м", "cargoClass": "3", "grossKg": 26, "otpusknaya": 83601, "smetnaya": 84703}, {"code": "241-302-0206", "name": "DN 600", "unit": "м", "cargoClass": "3", "grossKg": 38, "otpusknaya": 103991, "smetnaya": 105385}, {"code": "241-302-0207", "name": "DN 700", "unit": "м", "cargoClass": "3", "grossKg": 51, "otpusknaya": 129027, "smetnaya": 130771}, {"code": "241-302-0208", "name": "DN 800", "unit": "м", "cargoClass": "3", "grossKg": 67, "otpusknaya": 158220, "smetnaya": 160375}, {"code": "241-302-0209", "name": "DN 900", "unit": "м", "cargoClass": "3", "grossKg": 84, "otpusknaya": 191088, "smetnaya": 193703}, {"code": "241-302-0210", "name": "DN 1000", "unit": "м", "cargoClass": "3", "grossKg": 104, "otpusknaya": 201668, "smetnaya": 204487}, {"code": "241-302-0211", "name": "DN 1200", "unit": "м", "cargoClass": "3", "grossKg": 149, "otpusknaya": 229415, "smetnaya": 232739}, {"code": "241-302-0212", "name": "DN 1400", "unit": "м", "cargoClass": "3", "grossKg": 201, "otpusknaya": 301863, "smetnaya": 306256}, {"code": "241-302-0213", "name": "DN 1600", "unit": "м", "cargoClass": "3", "grossKg": 271, "otpusknaya": 365254, "smetnaya": 370676}, {"code": "241-302-0214", "name": "DN 1800", "unit": "м", "cargoClass": "3", "grossKg": 333, "otpusknaya": 405433, "smetnaya": 411574}, {"code": "241-302-0215", "name": "DN 2000", "unit": "м", "cargoClass": "3", "grossKg": 411, "otpusknaya": 617183, "smetnaya": 626165}, {"code": "241-302-0216", "name": "DN 2200", "unit": "м", "cargoClass": "3", "grossKg": 507, "otpusknaya": 742312, "smetnaya": 753164}, {"code": "241-302-0217", "name": "DN 2400", "unit": "м", "cargoClass": "3", "grossKg": 576, "otpusknaya": 883052, "smetnaya": 895857}, {"code": "241-302-0220", "name": "DN 3000", "unit": "м", "cargoClass": "3", "grossKg": 645, "otpusknaya": 1365284, "smetnaya": 1384140}, {"code": "241-302-0300", "name": "Труба пластиковая армированная стекловолокном с муфтой для водоснабжения, SN 5000, PN 10 СТ РК 1128-2002", "unit": "м", "isGroup": true}, {"code": "241-302-0301", "name": "DN 300", "unit": "м", "cargoClass": "3", "grossKg": 8, "otpusknaya": 50202, "smetnaya": 50835}, {"code": "241-302-0302", "name": "DN 350", "unit": "м", "cargoClass": "3", "grossKg": 10, "otpusknaya": 57806, "smetnaya": 58538}, {"code": "241-302-0303", "name": "DN 400", "unit": "м", "cargoClass": "3", "grossKg": 13, "otpusknaya": 65942, "smetnaya": 66783}, {"code": "241-302-0305", "name": "DN 500", "unit": "м", "cargoClass": "3", "grossKg": 20, "otpusknaya": 84132, "smetnaya": 85218}, {"code": "241-302-0306", "name": "DN 600", "unit": "м", "cargoClass": "3", "grossKg": 30, "otpusknaya": 104528, "smetnaya": 105897}, {"code": "241-302-0307", "name": "DN 700", "unit": "м", "cargoClass": "3", "grossKg": 40, "otpusknaya": 129791, "smetnaya": 131502}, {"code": "241-302-0308", "name": "DN 800", "unit": "м", "cargoClass": "3", "grossKg": 51, "otpusknaya": 159472, "smetnaya": 161581}, {"code": "241-302-0309", "name": "DN 900", "unit": "м", "cargoClass": "3", "grossKg": 65, "otpusknaya": 192958, "smetnaya": 195522}, {"code": "241-302-0310", "name": "DN 1000", "unit": "м", "cargoClass": "3", "grossKg": 80, "otpusknaya": 203755, "smetnaya": 206506}, {"code": "241-302-0311", "name": "DN 1200", "unit": "м", "cargoClass": "3", "grossKg": 115, "otpusknaya": 231709, "smetnaya": 234931}, {"code": "241-302-0312", "name": "DN 1400", "unit": "м", "cargoClass": "3", "grossKg": 155, "otpusknaya": 304882, "smetnaya": 309135}, {"code": "241-302-0313", "name": "DN 1600", "unit": "м", "cargoClass": "3", "grossKg": 205, "otpusknaya": 368907, "smetnaya": 374120}, {"code": "241-302-0314", "name": "DN 1800", "unit": "м", "cargoClass": "3", "grossKg": 255, "otpusknaya": 409487, "smetnaya": 415378}, {"code": "241-302-0315", "name": "DN 2000", "unit": "м", "cargoClass": "3", "grossKg": 315, "otpusknaya": 621746, "smetnaya": 630415}, {"code": "241-302-0316", "name": "DN 2200", "unit": "м", "cargoClass": "3", "grossKg": 375, "otpusknaya": 747630, "smetnaya": 758039}, {"code": "241-302-0317", "name": "DN 2400", "unit": "м", "cargoClass": "3", "grossKg": 453, "otpusknaya": 888781, "smetnaya": 901183}, {"code": "241-302-0320", "name": "DN 3000", "unit": "м", "cargoClass": "3", "grossKg": 690, "otpusknaya": 1370731, "smetnaya": 1389825}, {"code": "241-302-0400", "name": "Труба пластиковая армированная стекловолокном с муфтой для водоснабжения, SN 5000, PN 16 СТ РК 1128-2002", "unit": "м", "isGroup": true}, {"code": "241-302-0401", "name": "DN 300", "unit": "м", "cargoClass": "3", "grossKg": 9, "otpusknaya": 52169, "smetnaya": 52830}, {"code": "241-302-0402", "name": "DN 350", "unit": "м", "cargoClass": "3", "grossKg": 13, "otpusknaya": 60267, "smetnaya": 61040}, {"code": "241-302-0403", "name": "DN 400", "unit": "м", "cargoClass": "3", "grossKg": 16, "otpusknaya": 69069, "smetnaya": 69959}, {"code": "241-302-0405", "name": "DN 500", "unit": "м", "cargoClass": "3", "grossKg": 25, "otpusknaya": 89422, "smetnaya": 90591}, {"code": "241-302-0406", "name": "DN 600", "unit": "м", "cargoClass": "3", "grossKg": 33, "otpusknaya": 111720, "smetnaya": 113187}, {"code": "241-302-0407", "name": "DN 700", "unit": "м", "cargoClass": "3", "grossKg": 44, "otpusknaya": 139726, "smetnaya": 141572}, {"code": "241-302-0408", "name": "DN 800", "unit": "м", "cargoClass": "3", "grossKg": 57, "otpusknaya": 172036, "smetnaya": 174319}, {"code": "241-302-0409", "name": "DN 900", "unit": "м", "cargoClass": "3", "grossKg": 72, "otpusknaya": 207993, "smetnaya": 210765}, {"code": "241-302-0410", "name": "DN 1000", "unit": "м", "cargoClass": "3", "grossKg": 89, "otpusknaya": 219983, "smetnaya": 222964}, {"code": "241-302-0411", "name": "DN 1200", "unit": "м", "cargoClass": "3", "grossKg": 126, "otpusknaya": 234026, "smetnaya": 237318}, {"code": "241-302-0412", "name": "DN 1400", "unit": "м", "cargoClass": "3", "grossKg": 171, "otpusknaya": 307931, "smetnaya": 312281}, {"code": "241-302-0413", "name": "DN 1600", "unit": "м", "cargoClass": "3", "grossKg": 222, "otpusknaya": 372596, "smetnaya": 377918}, {"code": "241-302-0414", "name": "DN 1800", "unit": "м", "cargoClass": "3", "grossKg": 280, "otpusknaya": 413582, "smetnaya": 419618}, {"code": "241-302-0415", "name": "DN 2000", "unit": "м", "cargoClass": "3", "grossKg": 345, "otpusknaya": 681655, "smetnaya": 691158}, {"code": "241-302-0416", "name": "DN 2200", "unit": "м", "cargoClass": "3", "grossKg": 416, "otpusknaya": 818753, "smetnaya": 830173}, {"code": "241-302-0417", "name": "DN 2400", "unit": "м", "cargoClass": "3", "grossKg": 495, "otpusknaya": 970328, "smetnaya": 983869}, {"code": "241-302-0420", "name": "DN 3000", "unit": "м", "cargoClass": "3", "grossKg": 770, "otpusknaya": 1492950, "smetnaya": 1513818}, {"code": "241-302-0500", "name": "Труба пластиковая армированная стекловолокном с муфтой для водоснабжения, SN 10000, PN 1 СТ РК 1128-2002", "unit": "м", "isGroup": true}, {"code": "241-302-0501", "name": "DN 300", "unit": "м", "cargoClass": "3", "grossKg": 12, "otpusknaya": 55340, "smetnaya": 56050}, {"code": "241-302-0502", "name": "DN 350", "unit": "м", "cargoClass": "3", "grossKg": 16, "otpusknaya": 64066, "smetnaya": 64896}, {"code": "241-302-0503", "name": "DN 400", "unit": "м", "cargoClass": "3", "grossKg": 21, "otpusknaya": 73405, "smetnaya": 74367}, {"code": "241-302-0505", "name": "DN 500", "unit": "м", "cargoClass": "3", "grossKg": 32, "otpusknaya": 94706, "smetnaya": 95966}, {"code": "241-302-0506", "name": "DN 600", "unit": "м", "cargoClass": "3", "grossKg": 46, "otpusknaya": 118918, "smetnaya": 120522}, {"code": "241-302-0507", "name": "DN 700", "unit": "м", "cargoClass": "3", "grossKg": 63, "otpusknaya": 149130, "smetnaya": 151161}, {"code": "241-302-0508", "name": "DN 800", "unit": "м", "cargoClass": "3", "grossKg": 82, "otpusknaya": 183722, "smetnaya": 186241}, {"code": "241-302-0509", "name": "DN 900", "unit": "м", "cargoClass": "3", "grossKg": 104, "otpusknaya": 222595, "smetnaya": 225665}, {"code": "241-302-0510", "name": "DN 1000", "unit": "м", "cargoClass": "3", "grossKg": 128, "otpusknaya": 237094, "smetnaya": 240430}, {"code": "241-302-0511", "name": "DN 1200", "unit": "м", "cargoClass": "3", "grossKg": 184, "otpusknaya": 270301, "smetnaya": 274250}, {"code": "241-302-0512", "name": "DN 1400", "unit": "м", "cargoClass": "3", "grossKg": 214, "otpusknaya": 368981, "smetnaya": 374229}, {"code": "241-302-0513", "name": "DN 1600", "unit": "м", "cargoClass": "3", "grossKg": 231, "otpusknaya": 430349, "smetnaya": 436399}, {"code": "241-302-0514", "name": "DN 1800", "unit": "м", "cargoClass": "3", "grossKg": 325, "otpusknaya": 477688, "smetnaya": 484666}, {"code": "241-302-0515", "name": "DN 2000", "unit": "м", "cargoClass": "3", "grossKg": 394, "otpusknaya": 743711, "smetnaya": 754146}, {"code": "241-302-0516", "name": "DN 2200", "unit": "м", "cargoClass": "3", "grossKg": 464, "otpusknaya": 899020, "smetnaya": 911587}, {"code": "241-302-0517", "name": "DN 2400", "unit": "м", "cargoClass": "3", "grossKg": 577, "otpusknaya": 1077495, "smetnaya": 1092637}, {"code": "241-302-0600", "name": "Труба пластиковая армированная стекловолокном с муфтой для водоснабжения, SN 10000, PN 6 СТ РК 1128-2002", "unit": "м", "isGroup": true}, {"code": "241-302-0601", "name": "DN 300", "unit": "м", "cargoClass": "3", "grossKg": 9, "otpusknaya": 55383, "smetnaya": 56082}, {"code": "241-302-0602", "name": "DN 350", "unit": "м", "cargoClass": "3", "grossKg": 13, "otpusknaya": 64131, "smetnaya": 64951}, {"code": "241-302-0603", "name": "DN 400", "unit": "м", "cargoClass": "3", "grossKg": 16, "otpusknaya": 73481, "smetnaya": 74424}, {"code": "241-302-0605", "name": "DN 500", "unit": "м", "cargoClass": "3", "grossKg": 26, "otpusknaya": 94820, "smetnaya": 96058}, {"code": "241-302-0606", "name": "DN 600", "unit": "м", "cargoClass": "3", "grossKg": 37, "otpusknaya": 119075, "smetnaya": 120646}, {"code": "241-302-0607", "name": "DN 700", "unit": "м", "cargoClass": "3", "grossKg": 50, "otpusknaya": 149396, "smetnaya": 151380}, {"code": "241-302-0608", "name": "DN 800", "unit": "м", "cargoClass": "3", "grossKg": 65, "otpusknaya": 184231, "smetnaya": 186691}, {"code": "241-302-0609", "name": "DN 900", "unit": "м", "cargoClass": "3", "grossKg": 82, "otpusknaya": 223218, "smetnaya": 226211}, {"code": "241-302-0610", "name": "DN 1000", "unit": "м", "cargoClass": "3", "grossKg": 101, "otpusknaya": 237723, "smetnaya": 240963}, {"code": "241-302-0611", "name": "DN 1200", "unit": "м", "cargoClass": "3", "grossKg": 146, "otpusknaya": 273004, "smetnaya": 276840}, {"code": "241-302-0612", "name": "DN 1400", "unit": "м", "cargoClass": "3", "grossKg": 197, "otpusknaya": 388284, "smetnaya": 393698}, {"code": "241-302-0613", "name": "DN 1600", "unit": "м", "cargoClass": "3", "grossKg": 257, "otpusknaya": 434652, "smetnaya": 440854}, {"code": "241-302-0614", "name": "DN 1800", "unit": "м", "cargoClass": "3", "grossKg": 325, "otpusknaya": 482465, "smetnaya": 489500}, {"code": "241-302-0615", "name": "DN 2000", "unit": "м", "cargoClass": "3", "grossKg": 394, "otpusknaya": 745938, "smetnaya": 756400}, {"code": "241-302-0616", "name": "DN 2200", "unit": "м", "cargoClass": "3", "grossKg": 464, "otpusknaya": 901974, "smetnaya": 914577}, {"code": "241-302-0617", "name": "DN 2400", "unit": "м", "cargoClass": "3", "grossKg": 577, "otpusknaya": 1081175, "smetnaya": 1096362}, {"code": "241-302-0700", "name": "Труба пластиковая армированная стекловолокном с муфтой для водоснабжения, SN 10000, PN 10 СТ РК 1128-2002", "unit": "м", "isGroup": true}, {"code": "241-302-0701", "name": "DN 300", "unit": "м", "cargoClass": "3", "grossKg": 10, "otpusknaya": 55421, "smetnaya": 56125}, {"code": "241-302-0702", "name": "DN 350", "unit": "м", "cargoClass": "3", "grossKg": 14, "otpusknaya": 64191, "smetnaya": 65015}, {"code": "241-302-0703", "name": "DN 400", "unit": "м", "cargoClass": "3", "grossKg": 18, "otpusknaya": 73557, "smetnaya": 74509}, {"code": "241-302-0705", "name": "DN 500", "unit": "м", "cargoClass": "3", "grossKg": 28, "otpusknaya": 94934, "smetnaya": 96181}, {"code": "241-302-0706", "name": "DN 600", "unit": "м", "cargoClass": "3", "grossKg": 40, "otpusknaya": 119227, "smetnaya": 120811}, {"code": "241-302-0707", "name": "DN 700", "unit": "м", "cargoClass": "3", "grossKg": 54, "otpusknaya": 149656, "smetnaya": 151659}, {"code": "241-302-0708", "name": "DN 800", "unit": "м", "cargoClass": "3", "grossKg": 70, "otpusknaya": 184741, "smetnaya": 187226}, {"code": "241-302-0709", "name": "DN 900", "unit": "м", "cargoClass": "3", "grossKg": 88, "otpusknaya": 223836, "smetnaya": 226860}, {"code": "241-302-0710", "name": "DN 1000", "unit": "м", "cargoClass": "3", "grossKg": 109, "otpusknaya": 238351, "smetnaya": 241630}, {"code": "241-302-0711", "name": "DN 1200", "unit": "м", "cargoClass": "3", "grossKg": 157, "otpusknaya": 275734, "smetnaya": 279645}, {"code": "241-302-0712", "name": "DN 1400", "unit": "м", "cargoClass": "3", "grossKg": 213, "otpusknaya": 376434, "smetnaya": 381768}, {"code": "241-302-0713", "name": "DN 1600", "unit": "м", "cargoClass": "3", "grossKg": 277, "otpusknaya": 438999, "smetnaya": 445329}, {"code": "241-302-0714", "name": "DN 1800", "unit": "м", "cargoClass": "3", "grossKg": 351, "otpusknaya": 487289, "smetnaya": 494483}, {"code": "241-302-0715", "name": "DN 2000", "unit": "м", "cargoClass": "3", "grossKg": 425, "otpusknaya": 748166, "smetnaya": 758774}, {"code": "241-302-0716", "name": "DN 2200", "unit": "м", "cargoClass": "3", "grossKg": 495, "otpusknaya": 904928, "smetnaya": 917685}, {"code": "241-302-0717", "name": "DN 2400", "unit": "м", "cargoClass": "3", "grossKg": 567, "otpusknaya": 1084856, "smetnaya": 1100048}, {"code": "241-302-0800", "name": "Труба пластиковая армированная стекловолокном с муфтой для водоснабжения, SN 10000, PN 16 СТ РК 1128-2002", "unit": "м", "isGroup": true}, {"code": "241-302-0801", "name": "DN 300", "unit": "м", "cargoClass": "3", "grossKg": 9, "otpusknaya": 56240, "smetnaya": 56949}, {"code": "241-302-0802", "name": "DN 350", "unit": "м", "cargoClass": "3", "grossKg": 13, "otpusknaya": 65264, "smetnaya": 66097}, {"code": "241-302-0803", "name": "DN 400", "unit": "м", "cargoClass": "3", "grossKg": 16, "otpusknaya": 75091, "smetnaya": 76053}, {"code": "241-302-0805", "name": "DN 500", "unit": "м", "cargoClass": "3", "grossKg": 26, "otpusknaya": 97693, "smetnaya": 98965}, {"code": "241-302-0806", "name": "DN 600", "unit": "м", "cargoClass": "3", "grossKg": 37, "otpusknaya": 123471, "smetnaya": 125095}, {"code": "241-302-0807", "name": "DN 700", "unit": "м", "cargoClass": "3", "grossKg": 50, "otpusknaya": 155342, "smetnaya": 157398}, {"code": "241-302-0808", "name": "DN 800", "unit": "м", "cargoClass": "3", "grossKg": 65, "otpusknaya": 192367, "smetnaya": 194924}, {"code": "241-302-0809", "name": "DN 900", "unit": "м", "cargoClass": "3", "grossKg": 82, "otpusknaya": 233056, "smetnaya": 236167}, {"code": "241-302-0810", "name": "DN 1000", "unit": "м", "cargoClass": "3", "grossKg": 101, "otpusknaya": 247484, "smetnaya": 250841}, {"code": "241-302-0811", "name": "DN 1200", "unit": "м", "cargoClass": "3", "grossKg": 146, "otpusknaya": 278491, "smetnaya": 282393}, {"code": "241-302-0812", "name": "DN 1400", "unit": "м", "cargoClass": "3", "grossKg": 197, "otpusknaya": 380199, "smetnaya": 385516}, {"code": "241-302-0813", "name": "DN 1600", "unit": "м", "cargoClass": "3", "grossKg": 257, "otpusknaya": 443389, "smetnaya": 449695}, {"code": "241-302-0814", "name": "DN 1800", "unit": "м", "cargoClass": "3", "grossKg": 325, "otpusknaya": 492162, "smetnaya": 499314}, {"code": "241-302-0815", "name": "DN 2000", "unit": "м", "cargoClass": "3", "grossKg": 394, "otpusknaya": 780622, "smetnaya": 791500}, {"code": "241-302-0816", "name": "DN 2200", "unit": "м", "cargoClass": "3", "grossKg": 464, "otpusknaya": 940826, "smetnaya": 953895}, {"code": "241-302-0817", "name": "DN 2400", "unit": "м", "cargoClass": "3", "grossKg": 577, "otpusknaya": 1121306, "smetnaya": 1136974}, {"code": "241-302-0900", "name": "Труба пластиковая армированная стекловолокном с муфтой для канализации, SN 5000, PN 1 ГОСТ 31432-2011 (ISO 10467:2013)", "unit": "м", "isGroup": true}, {"code": "241-302-0901", "name": "DN 300", "unit": "м", "cargoClass": "3", "grossKg": 10, "otpusknaya": 49990, "smetnaya": 50628}, {"code": "241-302-0902", "name": "DN 350", "unit": "м", "cargoClass": "3", "grossKg": 13, "otpusknaya": 57367, "smetnaya": 58105}, {"code": "241-302-0903", "name": "DN 400", "unit": "м", "cargoClass": "3", "grossKg": 17, "otpusknaya": 65362, "smetnaya": 66211}, {"code": "241-302-0904", "name": "DN 500", "unit": "м", "cargoClass": "3", "grossKg": 26, "otpusknaya": 83064, "smetnaya": 84160}, {"code": "241-302-0905", "name": "DN 600", "unit": "м", "cargoClass": "3", "grossKg": 38, "otpusknaya": 103455, "smetnaya": 104842}, {"code": "241-302-0906", "name": "DN 700", "unit": "м", "cargoClass": "3", "grossKg": 51, "otpusknaya": 128263, "smetnaya": 129997}, {"code": "241-302-0907", "name": "DN 800", "unit": "м", "cargoClass": "3", "grossKg": 67, "otpusknaya": 156962, "smetnaya": 159103}, {"code": "241-302-0908", "name": "DN 900", "unit": "м", "cargoClass": "3", "grossKg": 84, "otpusknaya": 189212, "smetnaya": 191805}, {"code": "241-302-0909", "name": "DN 1000", "unit": "м", "cargoClass": "3", "grossKg": 104, "otpusknaya": 199576, "smetnaya": 202369}, {"code": "241-302-0910", "name": "DN 1200", "unit": "м", "cargoClass": "3", "grossKg": 149, "otpusknaya": 227144, "smetnaya": 230441}, {"code": "241-302-0911", "name": "DN 1400", "unit": "м", "cargoClass": "3", "grossKg": 201, "otpusknaya": 298874, "smetnaya": 303232}, {"code": "241-302-0912", "name": "DN 1600", "unit": "м", "cargoClass": "3", "grossKg": 271, "otpusknaya": 361638, "smetnaya": 367016}, {"code": "241-302-0913", "name": "DN 1800", "unit": "м", "cargoClass": "3", "grossKg": 333, "otpusknaya": 401418, "smetnaya": 407512}, {"code": "241-302-0914", "name": "DN 2000", "unit": "м", "cargoClass": "3", "grossKg": 411, "otpusknaya": 612613, "smetnaya": 621540}, {"code": "251-103-0200", "name": "Пластик и сопутствующие материалы для дорожной разметки СТ РК 2066-2010", "unit": "кг", "isGroup": true}, {"code": "251-103-0202", "name": "Термопластик для дорожной разметки ТР-АК с 20% содержанием стеклошариков", "unit": "кг", "cargoClass": "2", "grossKg": 1, "otpusknaya": 755, "smetnaya": 767}, {"code": "251-103-0203", "name": "Холодный пластик для дорожной разметки желтый", "unit": "кг", "cargoClass": "2", "grossKg": 1, "otpusknaya": 2386, "smetnaya": 2417}, {"code": "251-103-0204", "name": "Холодный пластик для дорожной разметки белый с отвердителем", "unit": "кг", "cargoClass": "2", "grossKg": 1, "otpusknaya": 1990, "smetnaya": 2017}, {"code": "251-103-0205", "name": "Холодный пластик для дорожной разметки желтый с отвердителем", "unit": "кг", "cargoClass": "2", "grossKg": 1, "otpusknaya": 2716, "smetnaya": 2752}, {"code": "251-103-0206", "name": "Микросферы стеклянные светоотражающие для дорожной разметки из пластика размерами от 450 мкм до 800 мкм", "unit": "кг", "cargoClass": "2", "grossKg": 1, "otpusknaya": 478, "smetnaya": 486}, {"code": "251-103-0207", "name": "Микросферы стеклянные светоотражающие для дорожной разметки из краски размерами от 100 мкм до 600 мкм", "unit": "кг", "cargoClass": "2", "grossKg": 1, "otpusknaya": 409, "smetnaya": 417}, {"code": "251-103-0208", "name": "Отвердитель холодного пластика для дорожной разметки", "unit": "кг", "cargoClass": "2", "grossKg": 1, "otpusknaya": 10551, "smetnaya": 10680}, {"code": "251-103-0209", "name": "Холодный пластик для дорожной разметки белый", "unit": "кг", "cargoClass": "2", "grossKg": 1, "otpusknaya": 1736, "smetnaya": 1759}, {"code": "251-103-0300", "name": "Краска для дорожной разметки СТ РК 2066-2010", "unit": "кг", "isGroup": true}, {"code": "251-103-0301", "name": "белая Сигнадор М", "unit": "кг", "cargoClass": "2", "grossKg": 1, "otpusknaya": 1872, "smetnaya": 1897}, {"code": "251-103-0302", "name": "желтая Сигнадор М", "unit": "кг", "cargoClass": "2", "grossKg": 1, "otpusknaya": 2000, "smetnaya": 2027}]}